autogen/__init__.py
autogen/autogen.py
autogen/defaultlog.py
autogen/import2pypi.txt
autogen/project.py
autogen/utils.py
autogen-1.0.14.dist-info/LICENCE.txt
autogen-1.0.14.dist-info/METADATA
autogen-1.0.14.dist-info/PKG-INFO-DESKTOP-M0MEAB0
autogen-1.0.14.dist-info/WHEEL
autogen-1.0.14.dist-info/entry_points.txt
autogen-1.0.14.dist-info/requires-DESKTOP-M0MEAB0.txt
autogen-1.0.14.dist-info/top_level.txt
autogen-1.0.14.dist-info/RECORD
