Metadata-Version: 2.1
Name: autogen
Version: 1.0.14
Summary: Automate development tasks
Home-page: https://gitlab.com/simonm3/autogen.git
License: UNKNOWN
Platform: UNKNOWN
License-File: LICENCE.txt
Requires-Dist: setuptools
Requires-Dist: docopt
Requires-Dist: PyYAML
Requires-Dist: autopep8
